poetry_dynamic_versioning/__init__.py
poetry_dynamic_versioning/__main__.py
poetry_dynamic_versioning/backend.py
poetry_dynamic_versioning/cli.py
poetry_dynamic_versioning/patch.py
poetry_dynamic_versioning/plugin.py
poetry_dynamic_versioning-1.9.0.dist-info/entry_points.txt
poetry_dynamic_versioning-1.9.0.dist-info/LICENSE
poetry_dynamic_versioning-1.9.0.dist-info/METADATA
poetry_dynamic_versioning-1.9.0.dist-info/WHEEL
poetry_dynamic_versioning-1.9.0.dist-info/RECORD
